prometheus_query_builder/__init__.py
prometheus_query_builder/label.py
prometheus_query_builder/query.py
prometheus_query_builder-0.1.4.dist-info/LICENSE
prometheus_query_builder-0.1.4.dist-info/WHEEL
prometheus_query_builder-0.1.4.dist-info/METADATA
prometheus_query_builder-0.1.4.dist-info/RECORD
