Metadata-Version: 2.1
Name: prometheus-query-builder
Version: 0.1.4
Summary: Package for generation Prometheus Query Language queries.
Home-page: https://github.com/m-chrome/prometheus-query-builder
License: MIT
Keywords: prometheus,promql,query-builder
Author: Michail Tsyganov
Author-email: tsyganov.michail@yandex.ru
Requires-Python: >=3.8,<4.0
Classifier: Development Status :: 3 - Alpha
Classifier: Intended Audience :: Developers
Classifier: License :: OSI Approved :: MIT License
Classifier: Operating System :: OS Independent
Classifier: Programming Language :: Python :: 3
Classifier: Programming Language :: Python :: 3 :: Only
Classifier: Programming Language :: Python :: 3.10
Classifier: Programming Language :: Python :: 3.8
Classifier: Programming Language :: Python :: 3.9
Project-URL: Bug Tracker, https://github.com/m-chrome/prometheus-query-builder/issues
Project-URL: Repository, https://github.com/m-chrome/prometheus-query-builder
